{
  "type": "minecraft:crafting_shapeless",
  "ingredients": [
    {
      "item": "minecraft:lily_pad"
    },
    {
      "tag": "forge:gems/mana"
    },
    {
      "tag": "forge:gems/mana"
    },
    {
      "tag": "forge:gems/mana"
    },
    {
      "tag": "forge:gems/mana"
    },
    {
      "tag": "forge:gems/mana"
    },
    {
      "tag": "forge:gems/mana"
    },
    {
      "tag": "forge:gems/mana"
    },
    {
      "tag": "forge:gems/mana"
    }
  ],
  "result": {
    "item": "ars_nouveau:lava_lily",
    "count": 8
  }
}