{
  "type": "ars_nouveau:enchantment",
  "enchantment": "minecraft:power",
  "level": 5,
  "mana": 9000,
  "item_1": [
    {
      "item": "ars_nouveau:glyph_amplify"
    }
  ],
  "item_2": [
    {
      "item": "ars_nouveau:glyph_amplify"
    }
  ],
  "item_3": [
    {
      "item": "ars_nouveau:glyph_amplify"
    }
  ],
  "item_4": [
    {
      "item": "ars_nouveau:glyph_amplify"
    }
  ],
  "item_5": [
    {
      "item": "ars_nouveau:glyph_amplify"
    }
  ],
  "item_6": [
    {
      "item": "ars_nouveau:glyph_projectile"
    }
  ],
  "item_7": [
    {
      "tag": "forge:storage_blocks/mana"
    }
  ],
  "item_8": [
    {
      "tag": "forge:storage_blocks/lapis"
    }
  ]
}