{
  "name": "Pierce",
  "icon": "ars_nouveau:glyph_pierce",
  "category": "spells_2",
  "sortnum": 3,
  "pages": [
    {
      "type": "text",
      "text": "When applied to the Projectile spell, projectiles may continue through their path an additional time after hitting a mob or block."
    },
    {
      "type": "glyph_recipe",
      "recipe": "ars_nouveau:glyph_pierce",
      "tier": "TWO",
      "mana_cost": "Medium",
      "clay_type": "ars_nouveau:marvelous_clay",
      "reagent": "minecraft:arrow"
    }
  ]
}