{
  "id": "ars_nouveau:block.ars_nouveau.relay",
  "icon": 100,
  "title": "Source Relay",
  "category": "ars_nouveau:source",
  "pages": [
    {
      "title": "Source Relay",
      "description": "Enables the transport of source between Source Jars and other Source Relays. To pull source from jars, use the Dominion Wand on the jar, and then on the relay. To send between relays or from a relay to a jar, use the wand on the relay and then the target you wish to send source to. Relays may only reach up to 30 blocks away. To clear connections, sneak while using the Dominion Wand on the relay.",
      "icon": "block.ars_nouveau.relay"
    }
  ]
}