{
  "name": "item.ars_nouveau.summon_focus",
  "icon": "ars_nouveau:summon_focus",
  "category": "equipment",
  "pages": [
    {
      "type": "text",
      "text": "A special casting focus. Grants summons from spells additional duration, strength, speed, and deals damage to enemies that kill them. Additionally, casting spells that target you like Self and Orbit will cast a copy of the spell on your nearby summons."
    },
    {
      "type": "apparatus_recipe",
      "recipe": "ars_nouveau:summon_focus"
    }
  ]
}